dragonfly_energy/__init__.py
dragonfly_energy/__main__.py
dragonfly_energy/_base.py
dragonfly_energy/_extend_dragonfly.py
dragonfly_energy/config.json
dragonfly_energy/config.py
dragonfly_energy/measure.py
dragonfly_energy/reopt.py
dragonfly_energy/run.py
dragonfly_energy/writer.py
dragonfly_energy/cli/__init__.py
dragonfly_energy/cli/install.py
dragonfly_energy/cli/simulate.py
dragonfly_energy/cli/translate.py
dragonfly_energy/des/__init__.py
dragonfly_energy/des/connector.py
dragonfly_energy/des/ghe.py
dragonfly_energy/des/junction.py
dragonfly_energy/des/loop.py
dragonfly_energy/opendss/__init__.py
dragonfly_energy/opendss/colorobj.py
dragonfly_energy/opendss/connector.py
dragonfly_energy/opendss/junction.py
dragonfly_energy/opendss/network.py
dragonfly_energy/opendss/powerline.py
dragonfly_energy/opendss/result.py
dragonfly_energy/opendss/road.py
dragonfly_energy/opendss/substation.py
dragonfly_energy/opendss/transformer.py
dragonfly_energy/opendss/transformerprop.py
dragonfly_energy/opendss/wire.py
dragonfly_energy/opendss/lib/__init__.py
dragonfly_energy/opendss/lib/extended_catalog.json
dragonfly_energy/opendss/lib/powerlines.py
dragonfly_energy/opendss/lib/transformers.py
dragonfly_energy/opendss/lib/wires.py
dragonfly_energy/properties/__init__.py
dragonfly_energy/properties/building.py
dragonfly_energy/properties/context.py
dragonfly_energy/properties/model.py
dragonfly_energy/properties/room2d.py
dragonfly_energy/properties/story.py
dragonfly_energy-1.35.82.dist-info/licenses/LICENSE
dragonfly_energy-1.35.82.dist-info/METADATA
dragonfly_energy-1.35.82.dist-info/WHEEL
dragonfly_energy-1.35.82.dist-info/entry_points.txt
dragonfly_energy-1.35.82.dist-info/top_level.txt
dragonfly_energy-1.35.82.dist-info/RECORD
