Metadata-Version: 2.4
Name: dragonfly-energy
Version: 1.35.82
Summary: Dragonfly extension for energy simulation.
Home-page: https://github.com/ladybug-tools/dragonfly-energy
Author: Ladybug Tools
Author-email: info@ladybug.tools
License: AGPL-3.0
Classifier: Programming Language :: Python :: 2.7
Classifier: Programming Language :: Python :: 3.7
Classifier: Programming Language :: Python :: 3.8
Classifier: Programming Language :: Python :: 3.9
Classifier: Programming Language :: Python :: 3.10
Classifier: Programming Language :: Python :: 3.11
Classifier: Programming Language :: Python :: 3.12
Classifier: Programming Language :: Python :: Implementation :: CPython
Classifier: Programming Language :: Python :: Implementation :: IronPython
Classifier: Operating System :: OS Independent
License-File: LICENSE
Requires-Dist: dragonfly-core==1.74.29
Requires-Dist: honeybee-energy==1.116.111
Provides-Extra: standards
Requires-Dist: honeybee-energy-standards==2.2.6; extra == "standards"
Provides-Extra: openstudio
Requires-Dist: honeybee-openstudio>=0.3.14; extra == "openstudio"
Dynamic: author
Dynamic: author-email
Dynamic: classifier
Dynamic: description
Dynamic: description-content-type
Dynamic: home-page
Dynamic: license
Dynamic: license-file
Dynamic: provides-extra
Dynamic: requires-dist
Dynamic: summary
